setup.py
jalaali/__init__.py
jalaali/jalaali.py
jalaali.egg-info/PKG-INFO
jalaali.egg-info/SOURCES.txt
jalaali.egg-info/dependency_links.txt
jalaali.egg-info/not-zip-safe
jalaali.egg-info/top_level.txt