Metadata-Version: 1.0
Name: jalaali
Version: 0.0.1
Summary: Python implementation of Jalali calendar
Home-page: https://github.com/aaghamohammadi/jalaali-python
Author: Alireza Aaghamohammadi
Author-email: al.aghamohammadi@gmail.com
License: MIT
Platform: UNKNOWN
